{
  "id": "Hydrographie:Surface hydrographique",
  "namespace": "Hydrographie",
  "name": "Surface hydrographique",
  "title": "Surface hydrographique",
  "description": "Zone  d'origine naturelle ou artificielle, temporaire ou permanente, couverte d'eau continentale de surface, douce ou salée ou couverte de glace persistante.",
  "properties": [
    {
      "name": "cleabs",
      "type": "string",
      "title": "Cleabs",
      "description": "Identifiant unique de l'objet correspondant."
    },
    {
      "name": "etat_de_l_objet",
      "type": "string",
      "title": "Etat de l'objet",
      "description": "Etat ou stade de la vie d'un objet qui peut être en projet, en construction ou en service.",
      "enum": [
        "En construction",
        "En projet",
        "En service"
      ]
    },
    {
      "name": "code_hydrographique",
      "type": "string",
      "title": "Code hydrographique",
      "description": "Identifiant de l'objet hydrographique."
    },
    {
      "name": "code_du_pays",
      "type": "string",
      "title": "Code du pays",
      "description": "Code du pays auquel appartient l'objet hydrographique."
    },
    {
      "name": "nature",
      "type": "string",
      "title": "Nature",
      "description": "Nature d'un objet  hydrographique.",
      "enum": [
        "Aqueduc",
        "Canal",
        "Conduit buse",
        "Conduit forcé",
        "Delta",
        "Ecoulement canalisé",
        "Ecoulement endoréique",
        "Ecoulement hyporhéique",
        "Ecoulement karstique",
        "Ecoulement naturel",
        "Ecoulement phréatique",
        "Estuaire",
        "Glacier, névé",
        "Inconnue",
        "Lac",
        "Lagon",
        "Lagune",
        "Mangrove",
        "Marais",
        "Mare",
        "Plan d'eau de gravière",
        "Plan d'eau de mine",
        "Ravine",
        "Réservoir-bassin",
        "Réservoir-bassin d'orage",
        "Réservoir-bassin piscicole",
        "Retenue",
        "Retenue-barrage",
        "Retenue-bassin portuaire",
        "Retenue-digue"
      ]
    },
    {
      "name": "position_par_rapport_au_sol",
      "type": "string",
      "title": "Position par rapport au sol",
      "description": "Niveau de l’objet par rapport à la surface du sol.",
      "enum": [
        "0",
        "-1",
        "1"
      ]
    },
    {
      "name": "statut",
      "type": "string",
      "title": "Statut de l'objet hydrographique",
      "description": "État de validité de l'objet hydrographique au sens du <a href=\"http://www.sandre.eaufrance.fr/?urn=urn:sandre:donnees:390::::::referentiel:3.1:html\">dictionnaire du SANDRE.</a>",
      "enum": [
        "Gelé",
        "Validé"
      ]
    },
    {
      "name": "persistance",
      "type": "string",
      "title": "Persistance",
      "description": "Degré de persistance de l'écoulement de l'eau.",
      "enum": [
        "Ephémère",
        "Inconnue",
        "Intermittent",
        "Permanent",
        "Sec"
      ]
    },
    {
      "name": "salinite",
      "type": "boolean",
      "title": "Salinité",
      "description": "Permet de préciser si la surface hydrographique est salée (Salinité=\"Vrai\") ou douce (Salinité=\"Faux\")."
    },
    {
      "name": "origine",
      "type": "string",
      "title": "Origine",
      "description": "Origine, naturelle ou artificielle, de la surface hydrographique.",
      "enum": [
        "Artificielle",
        "Inconnue",
        "Naturelle aménagée",
        "Naturelle non aménagée"
      ]
    },
    {
      "name": "cpx_toponyme_de_plan_d_eau",
      "type": "string",
      "title": "CPX_Toponyme de plan d'eau",
      "description": "Toponyme(s) du ou des <Plan d'eau> constitués par la surface hydrographique."
    },
    {
      "name": "cpx_toponyme_d_entite_de_transition",
      "type": "string",
      "title": "CPX_Toponyme d'entité de transition",
      "description": "Toponyme(s) de l'<Entité de transition> traversant la surface hydrographique."
    },
    {
      "name": "liens_vers_plan_d_eau",
      "type": "string",
      "title": "Liens vers plan d'eau",
      "description": "Identifiant (clé absolue) de l'objet <i>Plan d'eau</i> parent.\r\nUne surface hydrographique peut être liée avec 0 à n objets  <i>Plan d'eau</i>."
    },
    {
      "name": "lien_vers_entite_de_transition",
      "type": "string",
      "title": "Lien vers entité de transition",
      "description": "Identifiant de l'éventuel objet <Entité de transition> auquel appartient le tronçon hydrographique."
    },
    {
      "name": "geometrie",
      "type": "geometry",
      "title": "Géométrie",
      "description": ""
    }
  ]
}
