{
  "id": "BDCARTO_V5:detail_orographique",
  "namespace": "BDCARTO_V5",
  "name": "detail_orographique",
  "title": "BD CARTO® Détails orographiques",
  "description": "Détails orographiques - BD CARTO® V5 2025-09-15",
  "properties": [
    {
      "name": "cleabs",
      "type": "string"
    },
    {
      "name": "cote",
      "type": "integer"
    },
    {
      "name": "nature",
      "type": "string"
    },
    {
      "name": "toponyme",
      "type": "string"
    },
    {
      "name": "statut_du_toponyme",
      "type": "string"
    },
    {
      "name": "geometrie",
      "type": "point",
      "defaultCrs": "EPSG:4326"
    }
  ]
}