{
  "id": "ADMINEXPRESS-COG.2021:collectivite_territoriale",
  "namespace": "ADMINEXPRESS-COG.2021",
  "name": "collectivite_territoriale",
  "title": "ADMINEXPRESS COG 2021 Collectivité territoriale",
  "description": "ADMINEXPRESS COG 2021 Collectivité territoriale",
  "properties": [
    {
      "name": "id",
      "type": "string"
    },
    {
      "name": "nom",
      "type": "string"
    },
    {
      "name": "nom_m",
      "type": "string"
    },
    {
      "name": "insee_col",
      "type": "string"
    },
    {
      "name": "geom",
      "type": "multipolygon",
      "defaultCrs": "EPSG:4326"
    }
  ]
}